openalgo_backtrader-0.1.11.dist-info/licenses/LICENSE
openalgo_bt/__init__.py
openalgo_bt/brokers/__init__.py
openalgo_bt/brokers/oabroker.py
openalgo_bt/feeds/__init__.py
openalgo_bt/feeds/oa.py
openalgo_bt/stores/__init__.py
openalgo_bt/stores/oa.py
openalgo_bt/utils/history.py
openalgo_backtrader-0.1.11.dist-info/METADATA
openalgo_backtrader-0.1.11.dist-info/WHEEL
openalgo_backtrader-0.1.11.dist-info/top_level.txt
openalgo_backtrader-0.1.11.dist-info/RECORD
