Metadata-Version: 2.4
Name: openalgo-backtrader
Version: 0.1.11
Summary: Backtrader integration for OpenAlgo (India) - stores, feeds, and brokers
Author-email: Sudharsan Rangarajan <sudharsan.rangarajan@gmail.com>
Project-URL: Homepage, https://github.com/p2c2e/openalgo-backtrader
Requires-Python: >=3.8
License-File: LICENSE
Requires-Dist: openalgo>=1.0.29
Requires-Dist: python-dotenv
Requires-Dist: diskcache
Dynamic: license-file
